fast_job/__init__.py
fast_job/job_api.py
fast_job/job_schedule.py
fast_job/lock.py
fast_job/redis_job_store.py
fast_job/schema.py
fast_job/sonyflake/__init__.py
fast_job/sonyflake/about.py
fast_job/sonyflake/sonyflake.py
fast_job-0.2.1.dist-info/LICENSE.md
fast_job-0.2.1.dist-info/LICENSE
fast_job-0.2.1.dist-info/WHEEL
fast_job-0.2.1.dist-info/METADATA
fast_job-0.2.1.dist-info/RECORD
