Metadata-Version: 2.1
Name: fast-job
Version: 0.2.1
Summary: a distributed scheduled task scheduling component written for fast-api
Home-page: https://github.com/Euraxluo/fast_job
License: The MIT LICENSE
Author: Euraxluo
Author-email: euraxluo@qq.com
Requires-Python: >=3.6,<4.0
Classifier: License :: Other/Proprietary License
Classifier: Programming Language :: Python :: 3
Classifier: Programming Language :: Python :: 3.6
Classifier: Programming Language :: Python :: 3.7
Classifier: Programming Language :: Python :: 3.8
Classifier: Programming Language :: Python :: 3.9
Classifier: Programming Language :: Python :: 3.10
Requires-Dist: APScheduler (==3.7.0)
Requires-Dist: fastapi
Requires-Dist: pydantic (==1.9.0)
Requires-Dist: redis
Project-URL: Repository, https://github.com/Euraxluo/fast_job
